taimos_cdk/__init__.py
taimos_cdk/py.typed
taimos_cdk/_jsii/__init__.py
taimos_cdk/_jsii/taimos-cdk-constructs@1.6.0.jsii.tgz
taimos_cdk-1.6.0.dist-info/METADATA
taimos_cdk-1.6.0.dist-info/WHEEL
taimos_cdk-1.6.0.dist-info/top_level.txt
taimos_cdk-1.6.0.dist-info/RECORD
