Metadata-Version: 2.1
Name: taimos-cdk
Version: 1.6.0
Summary: Higher level constructs for AWS CDK
Home-page: https://github.com/taimos/cdk-constructs
Author: Thorsten Hoeger<thorsten.hoeger@taimos.de>
License: Apache-2.0
Project-URL: Source, https://github.com/taimos/cdk-constructs
Platform: UNKNOWN
Classifier: Intended Audience :: Developers
Classifier: Operating System :: OS Independent
Classifier: Programming Language :: JavaScript
Classifier: Programming Language :: Python :: 3 :: Only
Classifier: Programming Language :: Python :: 3.6
Classifier: Programming Language :: Python :: 3.7
Classifier: Programming Language :: Python :: 3.8
Classifier: Typing :: Typed
Classifier: License :: OSI Approved
Requires-Python: >=3.6
Requires-Dist: jsii (~=0.20.11)
Requires-Dist: publication (>=0.0.3)
Requires-Dist: aws-cdk.alexa-ask (>=1.19.0,~=1.19)
Requires-Dist: aws-cdk.aws-apigateway (>=1.19.0,~=1.19)
Requires-Dist: aws-cdk.aws-certificatemanager (>=1.19.0,~=1.19)
Requires-Dist: aws-cdk.aws-cloudformation (>=1.19.0,~=1.19)
Requires-Dist: aws-cdk.aws-cloudfront (>=1.19.0,~=1.19)
Requires-Dist: aws-cdk.aws-codebuild (>=1.19.0,~=1.19)
Requires-Dist: aws-cdk.aws-codecommit (>=1.19.0,~=1.19)
Requires-Dist: aws-cdk.aws-codepipeline (>=1.19.0,~=1.19)
Requires-Dist: aws-cdk.aws-codepipeline-actions (>=1.19.0,~=1.19)
Requires-Dist: aws-cdk.aws-ec2 (>=1.19.0,~=1.19)
Requires-Dist: aws-cdk.aws-ecr (>=1.19.0,~=1.19)
Requires-Dist: aws-cdk.aws-elasticloadbalancingv2 (>=1.19.0,~=1.19)
Requires-Dist: aws-cdk.aws-events-targets (>=1.19.0,~=1.19)
Requires-Dist: aws-cdk.aws-iam (>=1.19.0,~=1.19)
Requires-Dist: aws-cdk.aws-logs (>=1.19.0,~=1.19)
Requires-Dist: aws-cdk.aws-route53-patterns (>=1.19.0,~=1.19)
Requires-Dist: aws-cdk.aws-s3-deployment (>=1.19.0,~=1.19)
Requires-Dist: aws-cdk.aws-sam (>=1.19.0,~=1.19)
Requires-Dist: aws-cdk.aws-secretsmanager (>=1.19.0,~=1.19)
Requires-Dist: aws-cdk.aws-sns-subscriptions (>=1.19.0,~=1.19)
Requires-Dist: aws-cdk.core (>=1.19.0,~=1.19)
Requires-Dist: aws-cdk.custom-resources (>=1.19.0,~=1.19)
